lbwmath/__init__.py
lbwmath/math.py
lbwmath/cc/__init__.py
lbwmath/cc/ok.py
lbwmath/lbw/__init__.py
lbwmath/lbw/fftpack.py
lbwmath/lbw/fftpack_lite.cp37-win_amd64.pyd
lbwmath/lbw/helper.py
lbwmath/lbw/info.py
lbwmath-7.2.5.dist-info/METADATA
lbwmath-7.2.5.dist-info/RECORD
lbwmath-7.2.5.dist-info/WHEEL
lbwmath-7.2.5.dist-info/top_level.txt
