Metadata-Version: 2.1
Name: lbwmath
Version: 7.2.5
Summary: minke_math
Home-page: UNKNOWN
Author: libowei
Author-email: 913911037@qq.com
License: MIT Licence
Platform: any
